Workbook

Sheet LISTA
A1: CODIGO | B1: NRO ORIGINAL | C1: DESCRIPCION | D1: MARCA | E1: COSTO USD | F1: MARGEN | G1: PRECIO VENTA USD | H1: PRECIO VENTA BS | I1: PRECIO VENTA COP | J1: CANTIDAD_TOTAL
A2: SK1301A | C2: ABRAZADERA BARRA ESTABILIZADORA R-18/FUEGO | E2: 1.75 | F2: 0.3 | G2: =ROUND(E2*(1+F2),2) -> 2.28 | H2: =ROUND(G2*NOTAS!$B$2,2) -> 1644.67 | I2: =ROUND(G2*NOTAS!$B$3,0) -> 7407 | J2: 1
A3: 06-5A-14467 | C3: ABRAZADERA BARRA ESTABILIZADORA R-18/FUEGO | D3: SANFOR | E3: 1.75 | F3: 0.3 | G3: =ROUND(E3*(1+F3),2) -> 2.28 | H3: =ROUND(G3*NOTAS!$B$2,2) -> 1644.67 | I3: =ROUND(G3*NOTAS!$B$3,0) -> 7407 | J3: 1
C4: ABRAZADERA CENTRAL BARRA ESTABILIZADORA R-11/19 | E4: 1.75 | F4: 0.3 | G4: =ROUND(E4*(1+F4),2) -> 2.28 | H4: =ROUND(G4*NOTAS!$B$2,2) -> 1644.67 | I4: =ROUND(G4*NOTAS!$B$3,0) -> 7407 | J4: 4
A5: 12479 | C5: ABRAZADERA PUNTA BARRA ESTABILIZADORA R-11/19 | E5: 1.75 | F5: 0.3 | G5: =ROUND(E5*(1+F5),2) -> 2.28 | H5: =ROUND(G5*NOTAS!$B$2,2) -> 1644.67 | I5: =ROUND(G5*NOTAS!$B$3,0) -> 7407 | J5: 3
A6: SAE 25W-60 | C6: ACEITE CASTROL GTX | D6: CASTROL | E6: 14.6154 | F6: 0.3 | G6: =ROUND(E6*(1+F6),2) -> 19 | H6: =ROUND(G6*NOTAS!$B$2,2) -> 13705.57 | I6: =ROUND(G6*NOTAS!$B$3,0) -> 61729 | J6: 18
C7: ACOPLE CAJA DIRECCION CIELO | D7: KOREA | E7: 9.6154 | F7: 0.3 | G7: =ROUND(E7*(1+F7),2) -> 12.5 | H7: =ROUND(G7*NOTAS!$B$2,2) -> 9016.82 | I7: =ROUND(G7*NOTAS!$B$3,0) -> 40611 | J7: 4
C8: ACOPLE CAJA DIRECCION R-12 | D8: SANFOR | E8: 10 | F8: 0.3 | G8: =ROUND(E8*(1+F8),2) -> 13 | H8: =ROUND(G8*NOTAS!$B$2,2) -> 9377.49 | I8: =ROUND(G8*NOTAS!$B$3,0) -> 42235 | J8: 3
C9: ALFOMBRAS NEGRA CHEVROLET | D9: ZEGA | E9: 47.6923 | F9: 0.3 | G9: =ROUND(E9*(1+F9),2) -> 62 | H9: =ROUND(G9*NOTAS!$B$2,2) -> 44723.43 | I9: =ROUND(G9*NOTAS!$B$3,0) -> 201430 | J9: 1
C10: ALFOMBRAS NEGRA FIAT | D10: ZEGA | E10: 47.6923 | F10: 0.3 | G10: =ROUND(E10*(1+F10),2) -> 62 | H10: =ROUND(G10*NOTAS!$B$2,2) -> 44723.43 | I10: =ROUND(G10*NOTAS!$B$3,0) -> 201430 | J10: 1
C11: ALFOMBRAS NEGRA FORD | D11: ZEGA | E11: 46.1538 | F11: 0.3 | G11: =ROUND(E11*(1+F11),2) -> 60 | H11: =ROUND(G11*NOTAS!$B$2,2) -> 43280.74 | I11: =ROUND(G11*NOTAS!$B$3,0) -> 194932 | J11: 2
A12: 96314258 | C12: ALTERNADOR MATIZ POLEA SIMPLE EN V | D12: MIRE | E12: 57.6923 | F12: 0.3 | G12: =ROUND(E12*(1+F12),2) -> 75 | H12: =ROUND(G12*NOTAS!$B$2,2) -> 54100.92 | I12: =ROUND(G12*NOTAS!$B$3,0) -> 243665 | J12: 1
A13: GP30064..Y | C13: AMORTIGUADOR DELANTERO CORSA | D13: COFAP | E13: 25 | F13: 0.3 | G13: =ROUND(E13*(1+F13),2) -> 32.5 | H13: =ROUND(G13*NOTAS!$B$2,2) -> 23443.73 | I13: =ROUND(G13*NOTAS!$B$3,0) -> 105588 | J13: 1
A14: MP8148 | C14: AMORTIGUADOR DELANTERO CORSA | D14: BOGE | E14: 25 | F14: 0.3 | G14: =ROUND(E14*(1+F14),2) -> 32.5 | H14: =ROUND(G14*NOTAS!$B$2,2) -> 23443.73 | I14: =ROUND(G14*NOTAS!$B$3,0) -> 105588 | J14: 4
A15: MP8297 | C15: AMORTIGUADOR DELANTERO ECOSPORT | D15: BOGE | E15: 25 | F15: 0.3 | G15: =ROUND(E15*(1+F15),2) -> 32.5 | H15: =ROUND(G15*NOTAS!$B$2,2) -> 23443.73 | I15: =ROUND(G15*NOTAS!$B$3,0) -> 105588 | J15: 1
A16: 4337G | C16: AMORTIGUADOR DELANTERO R-TWINGO | D16: SACHS | E16: 25 | F16: 0.3 | G16: =ROUND(E16*(1+F16),2) -> 32.5 | H16: =ROUND(G16*NOTAS!$B$2,2) -> 23443.73 | I16: =ROUND(G16*NOTAS!$B$3,0) -> 105588 | J16: 1
A17: 902112 | B17: 2S65A406A10AE | C17: AMORTIGUADOR MALETA FIESTA 04/13 | D17: FORD | E17: 15 | F17: 0.3 | G17: =ROUND(E17*(1+F17),2) -> 19.5 | H17: =ROUND(G17*NOTAS!$B$2,2) -> 14066.24 | I17: =ROUND(G17*NOTAS!$B$3,0) -> 63353 | J17: 2
A18: DR.16030 C.Y | C18: AMORTIGUADOR MALETA F-UNO | D18: COFAP | E18: 10 | F18: 0.3 | G18: =ROUND(E18*(1+F18),2) -> 13 | H18: =ROUND(G18*NOTAS!$B$2,2) -> 9377.49 | I18: =ROUND(G18*NOTAS!$B$3,0) -> 42235 | J18: 10
A19: GB47798..Y | C19: AMORTIGUADOR TRASERO CORSA | D19: COFAP | E19: 15 | F19: 0.3 | G19: =ROUND(E19*(1+F19),2) -> 19.5 | H19: =ROUND(G19*NOTAS!$B$2,2) -> 14066.24 | I19: =ROUND(G19*NOTAS!$B$3,0) -> 63353 | J19: 5
A20: 832387 | C20: AMORTIGUADOR TRASERO ECOSPORT | D20: BOGE | E20: 15 | F20: 0.3 | G20: =ROUND(E20*(1+F20),2) -> 19.5 | H20: =ROUND(G20*NOTAS!$B$2,2) -> 14066.24 | I20: =ROUND(G20*NOTAS!$B$3,0) -> 63353 | J20: 6
A21: 832386 | C21: AMORTIGUADOR TRASERO FIESTA 04/13 | D21: BOGE | E21: 15 | F21: 0.3 | G21: =ROUND(E21*(1+F21),2) -> 19.5 | H21: =ROUND(G21*NOTAS!$B$2,2) -> 14066.24 | I21: =ROUND(G21*NOTAS!$B$3,0) -> 63353 | J21: 2
A22: 93740225 STD | C22: ANILLOS MOTOR AVEO 1.6 STD | D22: DAEWOO | E22: 20 | F22: 0.3 | G22: =ROUND(E22*(1+F22),2) -> 26 | H22: =ROUND(G22*NOTAS!$B$2,2) -> 18754.99 | I22: =ROUND(G22*NOTAS!$B$3,0) -> 84471 | J22: 1
A23: DA.6689 050 | C23: ANILLOS MOTOR CHEVETTE 1.6 81,98MM 050 F/F | D23: COFAP | E23: 20 | F23: 0.3 | G23: =ROUND(E23*(1+F23),2) -> 26 | H23: =ROUND(G23*NOTAS!$B$2,2) -> 18754.99 | I23: =ROUND(G23*NOTAS!$B$3,0) -> 84471 | J23: 3
A24: DA.6404 050 | C24: ANILLOS MOTOR CHEVETTE 1.6 81,98MM 050 F/G | D24: COFAP | E24: 20 | F24: 0.3 | G24: =ROUND(E24*(1+F24),2) -> 26 | H24: =ROUND(G24*NOTAS!$B$2,2) -> 18754.99 | I24: =ROUND(G24*NOTAS!$B$3,0) -> 84471 | J24: 10
A25: DA.6404 075 | C25: ANILLOS MOTOR CHEVETTE 1.6 81,98MM 075 F/G | D25: COFAP | E25: 20 | F25: 0.3 | G25: =ROUND(E25*(1+F25),2) -> 26 | H25: =ROUND(G25*NOTAS!$B$2,2) -> 18754.99 | I25: =ROUND(G25*NOTAS!$B$3,0) -> 84471 | J25: 8
A26: DA.6689 100 | C26: ANILLOS MOTOR CHEVETTE 1.6 81,98MM 100 F/F | D26: COFAP | E26: 20 | F26: 0.3 | G26: =ROUND(E26*(1+F26),2) -> 26 | H26: =ROUND(G26*NOTAS!$B$2,2) -> 18754.99 | I26: =ROUND(G26*NOTAS!$B$3,0) -> 84471 | J26: 1
A27: DA.6404 100 | C27: ANILLOS MOTOR CHEVETTE 1.6 81,98MM 100 F/G | D27: COFAP | E27: 20 | F27: 0.3 | G27: =ROUND(E27*(1+F27),2) -> 26 | H27: =ROUND(G27*NOTAS!$B$2,2) -> 18754.99 | I27: =ROUND(G27*NOTAS!$B$3,0) -> 84471 | J27: 3
A28: DA.6404 STD | C28: ANILLOS MOTOR CHEVETTE 1.6 81,98MM STD F/G | D28: COFAP | E28: 20 | F28: 0.3 | G28: =ROUND(E28*(1+F28),2) -> 26 | H28: =ROUND(G28*NOTAS!$B$2,2) -> 18754.99 | I28: =ROUND(G28*NOTAS!$B$3,0) -> 84471 | J28: 5
A29: CA.4990 STD | C29: ANILLOS MOTOR CHEVETTE 1.6 82MM STD G/G | D29: COFAP | E29: 20 | F29: 0.3 | G29: =ROUND(E29*(1+F29),2) -> 26 | H29: =ROUND(G29*NOTAS!$B$2,2) -> 18754.99 | I29: =ROUND(G29*NOTAS!$B$3,0) -> 84471 | J29: 0
... A98: 4218003 | C98: ANTENA TECHO CORSA 2PTAS | D98: BRITE | E98: 6.1538 | F98: 0.3 | G98: =ROUND(E98*(1+F98),2) -> 8 | H98: =ROUND(G98*NOTAS!$B$2,2) -> 5770.76 | I98: =ROUND(G98*NOTAS!$B$3,0) -> 25991 | J98: 1
C99: ANTENA TECHO CORSA 2PTAS | D99: NSN | E99: 6.1538 | F99: 0.3 | G99: =ROUND(E99*(1+F99),2) -> 8 | H99: =ROUND(G99*NOTAS!$B$2,2) -> 5770.76 | I99: =ROUND(G99*NOTAS!$B$3,0) -> 25991 | J99: 1
A100: 11093042 | C100: ARANDELA BOMBA ACEITE CIELO/LANOS/CORSA | D100: GM | E100: 2.3077 | F100: 0.3 | G100: =ROUND(E100*(1+F100),2) -> 3 | H100: =ROUND(G100*NOTAS!$B$2,2) -> 2164.04 | I100: =ROUND(G100*NOTAS!$B$3,0) -> 9747 | J100: 20
A101: 266 | C101: ARBOL DE LEVA CHEVETTE 1.6 | D101: APLIC | E101: 70 | F101: 0.3 | G101: =ROUND(E101*(1+F101),2) -> 91 | H101: =ROUND(G101*NOTAS!$B$2,2) -> 65642.45 | I101: =ROUND(G101*NOTAS!$B$3,0) -> 295647 | J101: 4
A102: 133 | C102: ARBOL DE LEVA CORCEL | D102: APLIC | E102: 26 | F102: 0.3 | G102: =ROUND(E102*(1+F102),2) -> 33.8 | H102: =ROUND(G102*NOTAS!$B$2,2) -> 24381.48 | I102: =ROUND(G102*NOTAS!$B$3,0) -> 109812 | J102: 1
A103: 312 | C103: ARBOL DE LEVA F-147/UNO 1.3 | D103: APLIC | E103: 70 | F103: 0.3 | G103: =ROUND(E103*(1+F103),2) -> 91 | H103: =ROUND(G103*NOTAS!$B$2,2) -> 65642.45 | I103: =ROUND(G103*NOTAS!$B$3,0) -> 295647 | J103: 2
A104: 900108 | C104: ARBOL DE LEVA FIESTA/KA 1.6 OXIDADO | D104: FORD | E104: 70 | F104: 0.3 | G104: =ROUND(E104*(1+F104),2) -> 91 | H104: =ROUND(G104*NOTAS!$B$2,2) -> 65642.45 | I104: =ROUND(G104*NOTAS!$B$3,0) -> 295647 | J104: 2
A105: 339 | C105: ARBOL DE LEVA F-PALIO/SIENA 1.3 16V FIRE ADMICION | D105: APLIC | E105: 72 | F105: 0.3 | G105: =ROUND(E105*(1+F105),2) -> 93.6 | H105: =ROUND(G105*NOTAS!$B$2,2) -> 67517.95 | I105: =ROUND(G105*NOTAS!$B$3,0) -> 304094 | J105: 2
A106: 320 | C106: ARBOL DE LEVA F-PALIO/SIENA 1.3 8V MPI | D106: APLIC | E106: 70 | F106: 0.3 | G106: =ROUND(E106*(1+F106),2) -> 91 | H106: =ROUND(G106*NOTAS!$B$2,2) -> 65642.45 | I106: =ROUND(G106*NOTAS!$B$3,0) -> 295647 | J106: 2
A107: 93235615-1 | C107: ARBOL DE LEVA F-PALIO/SIENA 1.8 IDEA | D107: ZUTACA | E107: 50 | F107: 0.3 | G107: =ROUND(E107*(1+F107),2) -> 65 | H107: =ROUND(G107*NOTAS!$B$2,2) -> 46887.46 | I107: =ROUND(G107*NOTAS!$B$3,0) -> 211177 | J107: 1
A108: 267 | C108: ARBOL DE LEVA MONZA | D108: APLIC | E108: 70 | F108: 0.3 | G108: =ROUND(E108*(1+F108),2) -> 91 | H108: =ROUND(G108*NOTAS!$B$2,2) -> 65642.45 | I108: =ROUND(G108*NOTAS!$B$3,0) -> 295647 | J108: 3
A109: 90250034 | C109: ARO INTERMEDIO CIELO LANOS | D109: KOREA | E109: 4 | F109: 0.3 | G109: =ROUND(E109*(1+F109),2) -> 5.2 | H109: =ROUND(G109*NOTAS!$B$2,2) -> 3751 | I109: =ROUND(G109*NOTAS!$B$3,0) -> 16894 | J109: 10
C110: ARO SINCRONICO 1RA Y 2DA EXT CIELO/LANOS | D110: KOREA | E110: 9 | F110: 0.3 | G110: =ROUND(E110*(1+F110),2) -> 11.7 | H110: =ROUND(G110*NOTAS!$B$2,2) -> 8439.74 | I110: =ROUND(G110*NOTAS!$B$3,0) -> 38012 | J110: 10
A111: 9126089 | C111: ARO SINCRONICO 1RA Y 2DA EXT CORSA | D111: GM ORIG | E111: 10 | F111: 0.3 | G111: =ROUND(E111*(1+F111),2) -> 13 | H111: =ROUND(G111*NOTAS!$B$2,2) -> 9377.49 | I111: =ROUND(G111*NOTAS!$B$3,0) -> 42235 | J111: 10
A112: PL-360.02 | C112: ARO SINCRONICO 1RA Y 2DA F-UNO/PREMIO/REGATAPALIO/TEMPRA | D112: PLATINUM | E112: 9 | F112: 0.3 | G112: =ROUND(E112*(1+F112),2) -> 11.7 | H112: =ROUND(G112*NOTAS!$B$2,2) -> 8439.74 | I112: =ROUND(G112*NOTAS!$B$3,0) -> 38012 | J112: 2
A113: 7629336 | C113: ARO SINCRONICO 1RA Y 2DA F-UNO/PREMIO/REGATAPALIO/TEMPRA | D113: WOLF | E113: 9 | F113: 0.3 | G113: =ROUND(E113*(1+F113),2) -> 11.7 | H113: =ROUND(G113*NOTAS!$B$2,2) -> 8439.74 | I113: =ROUND(G113*NOTAS!$B$3,0) -> 38012 | J113: 1
C114: ARO SINCRONICO 1RA Y 2DA INT CIELO/LANOS | D114: KOREA | E114: 8 | F114: 0.3 | G114: =ROUND(E114*(1+F114),2) -> 10.4 | H114: =ROUND(G114*NOTAS!$B$2,2) -> 7501.99 | I114: =ROUND(G114*NOTAS!$B$3,0) -> 33788 | J114: 5
C115: ARO SINCRONICO 1RA Y 2DA R-19 | E115: 8 | F115: 0.3 | G115: =ROUND(E115*(1+F115),2) -> 10.4 | H115: =ROUND(G115*NOTAS!$B$2,2) -> 7501.99 | I115: =ROUND(G115*NOTAS!$B$3,0) -> 33788 | J115: 7
C116: ARO SINCRONICO 2DA R-12 | E116: 7 | F116: 0.3 | G116: =ROUND(E116*(1+F116),2) -> 9.1 | H116: =ROUND(G116*NOTAS!$B$2,2) -> 6564.24 | I116: =ROUND(G116*NOTAS!$B$3,0) -> 29565 | J116: 2
A117: PL-066.02 | C117: ARO SINCRONICO 3RA 4TA F-UNO/PREMIO/REGATA/PALIO/TEMPRA | D117: PLATINUM | E117: 4 | F117: 0.3 | G117: =ROUND(E117*(1+F117),2) -> 5.2 | H117: =ROUND(G117*NOTAS!$B$2,2) -> 3751 | I117: =ROUND(G117*NOTAS!$B$3,0) -> 16894 | J117: 4
A118: 38021R | C118: ARO SINCRONICO 3RA 4TA F-UNO/PREMIO/REGATA/PALIO/TEMPRA | D118: ITALY | E118: 4 | F118: 0.3 | G118: =ROUND(E118*(1+F118),2) -> 5.2 | H118: =ROUND(G118*NOTAS!$B$2,2) -> 3751 | I118: =ROUND(G118*NOTAS!$B$3,0) -> 16894 | J118: 2
A119: 94580747 | C119: ARO SINCRONICO 5TA CIELO/LANOS | D119: GM KOREA | E119: 4 | F119: 0.3 | G119: =ROUND(E119*(1+F119),2) -> 5.2 | H119: =ROUND(G119*NOTAS!$B$2,2) -> 3751 | I119: =ROUND(G119*NOTAS!$B$3,0) -> 16894 | J119: 2
A120: 90147286 | C120: ARO SINCRONICO 5TA CORSA | D120: GM ORIG | E120: 4 | F120: 0.3 | G120: =ROUND(E120*(1+F120),2) -> 5.2 | H120: =ROUND(G120*NOTAS!$B$2,2) -> 3751 | I120: =ROUND(G120*NOTAS!$B$3,0) -> 16894 | J120: 1
A121: PL-065.02 | C121: ARO SINCRONICO 5TA F-UNO/PREMIO/REGATAPALIO/TEMPRA | D121: PLATINUM | E121: 5 | F121: 0.3 | G121: =ROUND(E121*(1+F121),2) -> 6.5 | H121: =ROUND(G121*NOTAS!$B$2,2) -> 4688.75 | I121: =ROUND(G121*NOTAS!$B$3,0) -> 21118 | J121: 3
A122: 38032R | C122: ARO SINCRONICO 5TA F-UNO/PREMIO/REGATAPALIO/TEMPRA | D122: ITALY | E122: 5 | F122: 0.3 | G122: =ROUND(E122*(1+F122),2) -> 6.5 | H122: =ROUND(G122*NOTAS!$B$2,2) -> 4688.75 | I122: =ROUND(G122*NOTAS!$B$3,0) -> 21118 | J122: 2
A123: 41005 | C123: ARO SINCRONICO BRONCE LADA | D123: ITALY | E123: 10 | F123: 0.3 | G123: =ROUND(E123*(1+F123),2) -> 13 | H123: =ROUND(G123*NOTAS!$B$2,2) -> 9377.49 | I123: =ROUND(G123*NOTAS!$B$3,0) -> 42235 | J123: 2
A124: 14699 | C124: ARO SINCRONICO CHEVETTE | D124: IMCE | E124: 8 | F124: 0.3 | G124: =ROUND(E124*(1+F124),2) -> 10.4 | H124: =ROUND(G124*NOTAS!$B$2,2) -> 7501.99 | I124: =ROUND(G124*NOTAS!$B$3,0) -> 33788 | J124: 3
A125: 631608.11 | C125: ARO SINCRONICO CHEVETTE | D125: DIEHL | E125: 8 | F125: 0.3 | G125: =ROUND(E125*(1+F125),2) -> 10.4 | H125: =ROUND(G125*NOTAS!$B$2,2) -> 7501.99 | I125: =ROUND(G125*NOTAS!$B$3,0) -> 33788 | J125: 2
A126: 06-5A-51301 | C126: ASPA VENTILADOR CORCEL 3 HUECOS | D126: SANFOR | E126: 9.38 | F126: 0.3 | G126: =ROUND(E126*(1+F126),2) -> 12.19 | H126: =ROUND(G126*NOTAS!$B$2,2) -> 8793.2 | I126: =ROUND(G126*NOTAS!$B$3,0) -> 39604 | J126: 3
A127: 93741008 | C127: ASPA VENTILADOR MATIZ | D127: GM | E127: 18.89 | F127: 0.3 | G127: =ROUND(E127*(1+F127),2) -> 24.56 | H127: =ROUND(G127*NOTAS!$B$2,2) -> 17716.25 | I127: =ROUND(G127*NOTAS!$B$3,0) -> 79792 | J127: 2
A128: 2-13-048 | C128: ASPA VENTILADOR SWIFT | D128: SANFOR | E128: 15 | F128: 0.3 | G128: =ROUND(E128*(1+F128),2) -> 19.5 | H128: =ROUND(G128*NOTAS!$B$2,2) -> 14066.24 | I128: =ROUND(G128*NOTAS!$B$3,0) -> 63353 | J128: 1
... A148: BHPD3600 | C148: BANDA FRENOS TRASEROS R-19 1.4 | D148: BKPS | E148: 15 | F148: 0.3 | G148: =ROUND(E148*(1+F148),2) -> 19.5 | H148: =ROUND(G148*NOTAS!$B$2,2) -> 14066.24 | I148: =ROUND(G148*NOTAS!$B$3,0) -> 63353 | J148: 2
C149: BARRA ESTABILIZADORA KA | D149: FORD | E149: 26.9231 | F149: 0.3 | G149: =ROUND(E149*(1+F149),2) -> 35 | H149: =ROUND(G149*NOTAS!$B$2,2) -> 25247.1 | I149: =ROUND(G149*NOTAS!$B$3,0) -> 113710 | J149: 2
A150: 96653269 | C150: BASE AMORTIGUADOR DELANTERA AVEO | D150: KOREA | E150: 4 | F150: 0.3 | G150: =ROUND(E150*(1+F150),2) -> 5.2 | H150: =ROUND(G150*NOTAS!$B$2,2) -> 3751 | I150: =ROUND(G150*NOTAS!$B$3,0) -> 16894 | J150: 2
A151: 95015324 | C151: BASE AMORTIGUADOR DELANTERA AVEO ALTA | D151: PARTS-MALL | E151: 5 | F151: 0.3 | G151: =ROUND(E151*(1+F151),2) -> 6.5 | H151: =ROUND(G151*NOTAS!$B$2,2) -> 4688.75 | I151: =ROUND(G151*NOTAS!$B$3,0) -> 21118 | J151: 3
A152: 95015324 | C152: BASE AMORTIGUADOR DELANTERA AVEO ALTA | D152: GM | E152: 5 | F152: 0.3 | G152: =ROUND(E152*(1+F152),2) -> 6.5 | H152: =ROUND(G152*NOTAS!$B$2,2) -> 4688.75 | I152: =ROUND(G152*NOTAS!$B$3,0) -> 21118 | J152: 8
A153: 96653239 | C153: BASE AMORTIGUADOR DELANTERA AVEO ALTA | D153: GKP | E153: 4 | F153: 0.3 | G153: =ROUND(E153*(1+F153),2) -> 5.2 | H153: =ROUND(G153*NOTAS!$B$2,2) -> 3751 | I153: =ROUND(G153*NOTAS!$B$3,0) -> 16894 | J153: 1
A154: 92098953 | C154: BASE AMORTIGUADOR DELANTERA CORSA | E154: 4 | F154: 0.3 | G154: =ROUND(E154*(1+F154),2) -> 5.2 | H154: =ROUND(G154*NOTAS!$B$2,2) -> 3751 | I154: =ROUND(G154*NOTAS!$B$3,0) -> 16894 | J154: 1
A155: 92098953 | C155: BASE AMORTIGUADOR DELANTERA CORSA | D155: HITECH | E155: 4 | F155: 0.3 | G155: =ROUND(E155*(1+F155),2) -> 5.2 | H155: =ROUND(G155*NOTAS!$B$2,2) -> 3751 | I155: =ROUND(G155*NOTAS!$B$3,0) -> 16894 | J155: 0
A156: GKP-42-01330 | C156: BASE AMORTIGUADOR DELANTERA DERECHA F-PAL/SIE | D156: GKP | E156: 15 | F156: 0.3 | G156: =ROUND(E156*(1+F156),2) -> 19.5 | H156: =ROUND(G156*NOTAS!$B$2,2) -> 14066.24 | I156: =ROUND(G156*NOTAS!$B$3,0) -> 63353 | J156: 1
A157: 1308 | C157: BASE AMORTIGUADOR DELANTERA DERECHA F-PAL/SIE | D157: SAMPEL | E157: 25 | F157: 0.3 | G157: =ROUND(E157*(1+F157),2) -> 32.5 | H157: =ROUND(G157*NOTAS!$B$2,2) -> 23443.73 | I157: =ROUND(G157*NOTAS!$B$3,0) -> 105588 | J157: 4
A158: 1006 | C158: BASE AMORTIGUADOR DELANTERA F-147/SPAZIO | D158: SAMPEL | E158: 8 | F158: 0.3 | G158: =ROUND(E158*(1+F158),2) -> 10.4 | H158: =ROUND(G158*NOTAS!$B$2,2) -> 7501.99 | I158: =ROUND(G158*NOTAS!$B$3,0) -> 33788 | J158: 3
A159: 1013794 | B159: 96FB3K155AG | C159: BASE AMORTIGUADOR DELANTERA FIESTA …/03-KA | D159: FORD | E159: 12 | F159: 0.3 | G159: =ROUND(E159*(1+F159),2) -> 15.6 | H159: =ROUND(G159*NOTAS!$B$2,2) -> 11252.99 | I159: =ROUND(G159*NOTAS!$B$3,0) -> 50682 | J159: 1
A160: 2701A | B160: 96FB3K155AG | C160: BASE AMORTIGUADOR DELANTERA FIESTA …/03-KA CON ROLINERA | D160: SAMPEL | E160: 14 | F160: 0.3 | G160: =ROUND(E160*(1+F160),2) -> 18.2 | H160: =ROUND(G160*NOTAS!$B$2,2) -> 13128.49 | I160: =ROUND(G160*NOTAS!$B$3,0) -> 59129 | J160: 2
A161: 924785 | B161: 2S653K155CB | C161: BASE AMORTIGUADOR DELANTERA FIESTA 04/13-ECOSPORT | D161: FORD | E161: 15 | F161: 0.3 | G161: =ROUND(E161*(1+F161),2) -> 19.5 | H161: =ROUND(G161*NOTAS!$B$2,2) -> 14066.24 | I161: =ROUND(G161*NOTAS!$B$3,0) -> 63353 | J161: 2
A162: 2722B | C162: BASE AMORTIGUADOR DELANTERA FIESTA 04/13-ECOSPORT CON ROLINERA | D162: SAMPEL | E162: 18 | F162: 0.3 | G162: =ROUND(E162*(1+F162),2) -> 23.4 | H162: =ROUND(G162*NOTAS!$B$2,2) -> 16879.49 | I162: =ROUND(G162*NOTAS!$B$3,0) -> 76024 | J162: 1
A163: CF-1655-A | C163: BASE AMORTIGUADOR DELANTERA F-UNO/PREMIO | D163: CENTROFLEX | E163: 5 | F163: 0.3 | G163: =ROUND(E163*(1+F163),2) -> 6.5 | H163: =ROUND(G163*NOTAS!$B$2,2) -> 4688.75 | I163: =ROUND(G163*NOTAS!$B$3,0) -> 21118 | J163: 2
A164: 7583185-1 | C164: BASE AMORTIGUADOR DELANTERA F-UNO/PREMIO | D164: INROLCA | E164: 3 | F164: 0.3 | G164: =ROUND(E164*(1+F164),2) -> 3.9 | H164: =ROUND(G164*NOTAS!$B$2,2) -> 2813.25 | I164: =ROUND(G164*NOTAS!$B$3,0) -> 12671 | J164: 6
A165: 54610-22000 | C165: BASE AMORTIGUADOR DELANTERA HYUNDAI ACCENT/GETZ 1.6 | D165: KOREA | E165: 13 | F165: 0.3 | G165: =ROUND(E165*(1+F165),2) -> 16.9 | H165: =ROUND(G165*NOTAS!$B$2,2) -> 12190.74 | I165: =ROUND(G165*NOTAS!$B$3,0) -> 54906 | J165: 11
A166: 1307 | C166: BASE AMORTIGUADOR DELANTERA IZQUIERDA F-PAL/SIE | D166: SAMPEL | E166: 25 | F166: 0.3 | G166: =ROUND(E166*(1+F166),2) -> 32.5 | H166: =ROUND(G166*NOTAS!$B$2,2) -> 23443.73 | I166: =ROUND(G166*NOTAS!$B$3,0) -> 105588 | J166: 1
A167: 96444919 | C167: BASE AMORTIGUADOR DELANTERA IZQUIERDA LANOS | D167: CARDEX | E167: 12 | F167: 0.3 | G167: =ROUND(E167*(1+F167),2) -> 15.6 | H167: =ROUND(G167*NOTAS!$B$2,2) -> 11252.99 | I167: =ROUND(G167*NOTAS!$B$3,0) -> 50682 | J167: 1
A168: DA0146 | C168: BASE AMORTIGUADOR DELANTERA IZQUIERDA LANOS | D168: PROSHOCK | E168: 10 | F168: 0.3 | G168: =ROUND(E168*(1+F168),2) -> 13 | H168: =ROUND(G168*NOTAS!$B$2,2) -> 9377.49 | I168: =ROUND(G168*NOTAS!$B$3,0) -> 42235 | J168: 3
A169: P96549921 | C169: BASE AMORTIGUADOR DELANTERA OPTRA | D169: SBB | E169: 7 | F169: 0.3 | G169: =ROUND(E169*(1+F169),2) -> 9.1 | H169: =ROUND(G169*NOTAS!$B$2,2) -> 6564.24 | I169: =ROUND(G169*NOTAS!$B$3,0) -> 29565 | J169: 2
A170: 96549921 | C170: BASE AMORTIGUADOR DELANTERA OPTRA | D170: BOSUNGINDUS | E170: 10 | F170: 0.3 | G170: =ROUND(E170*(1+F170),2) -> 13 | H170: =ROUND(G170*NOTAS!$B$2,2) -> 9377.49 | I170: =ROUND(G170*NOTAS!$B$3,0) -> 42235 | J170: 2
A171: R.9-615 | C171: BASE AMORTIGUADOR DELANTERA R-11 | D171: TAKSIM GROUP | E171: 15 | F171: 0.3 | G171: =ROUND(E171*(1+F171),2) -> 19.5 | H171: =ROUND(G171*NOTAS!$B$2,2) -> 14066.24 | I171: =ROUND(G171*NOTAS!$B$3,0) -> 63353 | J171: 3
A172: 7700835254 | C172: BASE AMORTIGUADOR DELANTERA R-19 | D172: RENAULT | E172: 20 | F172: 0.3 | G172: =ROUND(E172*(1+F172),2) -> 26 | H172: =ROUND(G172*NOTAS!$B$2,2) -> 18754.99 | I172: =ROUND(G172*NOTAS!$B$3,0) -> 84471 | J172: 3
A173: R.19-503 | C173: BASE AMORTIGUADOR DELANTERA R-19 | D173: TAKSIM GROUP | E173: 15 | F173: 0.3 | G173: =ROUND(E173*(1+F173),2) -> 19.5 | H173: =ROUND(G173*NOTAS!$B$2,2) -> 14066.24 | I173: =ROUND(G173*NOTAS!$B$3,0) -> 63353 | J173: 7
... A203: 1000 | C203: BASE CAJA IZQUIERDA F-147/SPAZIO | D203: SAMPEL | E203: 15 | F203: 0.3 | G203: =ROUND(E203*(1+F203),2) -> 19.5 | H203: =ROUND(G203*NOTAS!$B$2,2) -> 14066.24 | I203: =ROUND(G203*NOTAS!$B$3,0) -> 63353 | J203: 1
A204: 2725 | B204: 96FB7M121A | C204: BASE CAJA IZQUIERDA FIESTA …/03 | D204: SAMPEL | E204: 20 | F204: 0.3 | G204: =ROUND(E204*(1+F204),2) -> 26 | H204: =ROUND(G204*NOTAS!$B$2,2) -> 18754.99 | I204: =ROUND(G204*NOTAS!$B$3,0) -> 84471 | J204: 2
A205: 96FB7M121A | C205: BASE CAJA IZQUIERDA FIESTA …/03 | D205: BBR | E205: 20 | F205: 0.3 | G205: =ROUND(E205*(1+F205),2) -> 26 | H205: =ROUND(G205*NOTAS!$B$2,2) -> 18754.99 | I205: =ROUND(G205*NOTAS!$B$3,0) -> 84471 | J205: 6
A206: 941127 | B206: 2S657M121AB | C206: BASE CAJA IZQUIERDA FIESTA 04/13 | D206: FORD | E206: 40 | F206: 0.3 | G206: =ROUND(E206*(1+F206),2) -> 52 | H206: =ROUND(G206*NOTAS!$B$2,2) -> 37509.97 | I206: =ROUND(G206*NOTAS!$B$3,0) -> 168941 | J206: 4
A207: 788 | C207: BASE CAJA IZQUIERDA F-PALIO/SIENA …/99 | D207: BFX | E207: 10 | F207: 0.3 | G207: =ROUND(E207*(1+F207),2) -> 13 | H207: =ROUND(G207*NOTAS!$B$2,2) -> 9377.49 | I207: =ROUND(G207*NOTAS!$B$3,0) -> 42235 | J207: 3
A208: 46444759 | C208: BASE CAJA IZQUIERDA F-PALIO/SIENA …/99 | D208: FIAT | E208: 10 | F208: 0.3 | G208: =ROUND(E208*(1+F208),2) -> 13 | H208: =ROUND(G208*NOTAS!$B$2,2) -> 9377.49 | I208: =ROUND(G208*NOTAS!$B$3,0) -> 42235 | J208: 4
A209: 1305 | C209: BASE CAJA IZQUIERDA F-PALIO/SIENA …/99 | D209: SAMPEL | E209: 10 | F209: 0.3 | G209: =ROUND(E209*(1+F209),2) -> 13 | H209: =ROUND(G209*NOTAS!$B$2,2) -> 9377.49 | I209: =ROUND(G209*NOTAS!$B$3,0) -> 42235 | J209: 8
A210: 1070 | C210: BASE CAJA IZQUIERDA F-PALIO/SIENA 1.3 16V FIRE | D210: SAMPEL | E210: 20 | F210: 0.3 | G210: =ROUND(E210*(1+F210),2) -> 26 | H210: =ROUND(G210*NOTAS!$B$2,2) -> 18754.99 | I210: =ROUND(G210*NOTAS!$B$3,0) -> 84471 | J210: 8
A211: 21830-22000 | C211: BASE CAJA IZQUIERDA HYUNDAI ACCENT | D211: KOREA | E211: 15 | F211: 0.3 | G211: =ROUND(E211*(1+F211),2) -> 19.5 | H211: =ROUND(G211*NOTAS!$B$2,2) -> 14066.24 | I211: =ROUND(G211*NOTAS!$B$3,0) -> 63353 | J211: 1
A212: 2717 | B212: XS516B032AC | C212: BASE CAJA IZQUIERDA KA | D212: SAMPEL | E212: 20 | F212: 0.3 | G212: =ROUND(E212*(1+F212),2) -> 26 | H212: =ROUND(G212*NOTAS!$B$2,2) -> 18754.99 | I212: =ROUND(G212*NOTAS!$B$3,0) -> 84471 | J212: 4
A213: 96314472 | C213: BASE CAJA IZQUIERDA MATIZ | D213: WOORI CHEMICAL | E213: 10 | F213: 0.3 | G213: =ROUND(E213*(1+F213),2) -> 13 | H213: =ROUND(G213*NOTAS!$B$2,2) -> 9377.49 | I213: =ROUND(G213*NOTAS!$B$3,0) -> 42235 | J213: 1
A214: GM0280 | C214: BASE CAJA IZQUIERDA MONTANA MERIVA | D214: PROSHOCK | E214: 14 | F214: 0.3 | G214: =ROUND(E214*(1+F214),2) -> 18.2 | H214: =ROUND(G214*NOTAS!$B$2,2) -> 13128.49 | I214: =ROUND(G214*NOTAS!$B$3,0) -> 59129 | J214: 1
A215: 96550234 | C215: BASE CAJA IZQUIERDA OPTRA | D215: KAPARS | E215: 25 | F215: 0.3 | G215: =ROUND(E215*(1+F215),2) -> 32.5 | H215: =ROUND(G215*NOTAS!$B$2,2) -> 23443.73 | I215: =ROUND(G215*NOTAS!$B$3,0) -> 105588 | J215: 2
A216: RE0139 | C216: BASE CAJA IZQUIERDA R-11 | D216: PROSHOCK | E216: 5 | F216: 0.3 | G216: =ROUND(E216*(1+F216),2) -> 6.5 | H216: =ROUND(G216*NOTAS!$B$2,2) -> 4688.75 | I216: =ROUND(G216*NOTAS!$B$3,0) -> 21118 | J216: 10
...

Sheet NOTAS
A1: PARÁMETROS DE CONVERSIÓN — editar las celdas amarillas recalcula toda la lista
A2: Tasa Bs/USD (BCV) | B2: 721.3456 | C2: Banco Central de Venezuela, tipo de cambio de referencia del 13-07-2026 (bcv.org.ve via bcv.today)
A3: Tasa COP/USD (TRM) | B3: 3248.87 | C3: TRM oficial Colombia vigente desde el 11-07-2026, Superfinanciera (datos.gov.co)
A5: COSTO USD: dato original del archivo (la columna decía Bs pero estaba en dólares).
A6: MARGEN: margen de venta fijo del 30%, el mismo aplicado en data/raw_ventas.xlsx.
A7: PRECIO VENTA USD = COSTO USD × (1+MARGEN); BS y COP se calculan con las tasas de arriba.
